epub2pdf.py
epub2pdf-0.1.0.dist-info/METADATA
epub2pdf-0.1.0.dist-info/WHEEL
epub2pdf-0.1.0.dist-info/entry_points.txt
epub2pdf-0.1.0.dist-info/top_level.txt
epub2pdf-0.1.0.dist-info/RECORD
