Metadata-Version: 2.1
Name: epub2pdf
Version: 0.1.0
Summary: Convert fixed-layout manga/comic files(epub, azw3, mobi) to PDF file.
Home-page: https://github.com/mashu3/epub2pdf
Author: mashu3
License: GPLv3
Keywords: epub mobi azw3 pdf converter
Requires-Dist: lxml
Requires-Dist: mobi
Requires-Dist: Pillow
Requires-Dist: pikepdf
Requires-Dist: img2pdf
